list_test_poetry/__init__.py
list_test_poetry/__main__.py
list_test_poetry/list.json
list_test_poetry/list.txt
list_test_poetry-0.1.0.dist-info/entry_points.txt
list_test_poetry-0.1.0.dist-info/METADATA
list_test_poetry-0.1.0.dist-info/WHEEL
list_test_poetry-0.1.0.dist-info/RECORD
