Metadata-Version: 2.1
Name: list-test-poetry
Version: 0.1.0
Summary: 
Author: cybernight
Requires-Python: >=3.12,<4.0
Classifier: Programming Language :: Python :: 3
Classifier: Programming Language :: Python :: 3.12
Requires-Dist: pytest (>=7.4.3,<8.0.0)
